<?xml version="1.0" encoding="UTF-8" standalone="yes" ?>
<vjax:CountryIpMappings xmlns:vjax="http://www.flemax.com/2011/vjax" class="com.anosym.utilities.geocode.CountryIpMappings" ref-id="1354730556">
   <vjax:ipMappings class="java.util.HashMap" ref-id="1334829198" map="true">
      <vjax:map-entry>
         <vjax:key class="com.anosym.utilities.geocode.Ipv4Range" key="true" ref-id="1009078011">
            <vjax:origin class="com.anosym.utilities.geocode.Ipv4" ref-id="1860154224">
               <vjax:firstOctet class="java.lang.Integer" ref-id="545109742">125</vjax:firstOctet>
               <vjax:secondOctet class="java.lang.Integer" ref-id="494195692">254</vjax:secondOctet>
               <vjax:thirdOctet class="java.lang.Integer" ref-id="1627732495">60</vjax:thirdOctet>
               <vjax:fourthOctet class="java.lang.Integer" ref-id="505864332">0</vjax:fourthOctet>
            </vjax:origin>
            <vjax:end class="com.anosym.utilities.geocode.Ipv4" ref-id="174069451">
               <vjax:firstOctet class="java.lang.Integer" ref-id="712535743">125</vjax:firstOctet>
               <vjax:secondOctet class="java.lang.Integer" ref-id="1219416929">254</vjax:secondOctet>
               <vjax:thirdOctet class="java.lang.Integer" ref-id="1303882382">127</vjax:thirdOctet>
               <vjax:fourthOctet class="java.lang.Integer" ref-id="1428060286">255</vjax:fourthOctet>
            </vjax:end>
         </vjax:key>
         <vjax:value class="com.anosym.utilities.geocode.CountryIpMapping" value="true" ref-id="1131987930">
            <vjax:ipv4Range class="com.anosym.utilities.geocode.Ipv4Range" references="1009078011"/>
            <vjax:countryCode class="com.anosym.utilities.geocode.CountryCode" ref-id="2106830344">
               <vjax:isoCode class="java.lang.String" ref-id="1787219872">AU</vjax:isoCode>
               <vjax:isoCode2 class="java.lang.String" ref-id="950618115">AUS</vjax:isoCode2>
               <vjax:internationalDialingCode class="java.lang.String" ref-id="463697647">61</vjax:internationalDialingCode>
               <vjax:name class="java.lang.String" ref-id="148198166">Australia</vjax:name>
            </vjax:countryCode>
         </vjax:value>
      </vjax:map-entry>
      <vjax:map-entry>
         <vjax:key class="com.anosym.utilities.geocode.Ipv4Range" key="true" ref-id="1182880651">
            <vjax:origin class="com.anosym.utilities.geocode.Ipv4" ref-id="763510737">
               <vjax:firstOctet class="java.lang.Integer" ref-id="1110165934">125</vjax:firstOctet>
               <vjax:secondOctet class="java.lang.Integer" ref-id="1220927602">254</vjax:secondOctet>
               <vjax:thirdOctet class="java.lang.Integer" ref-id="923959729">52</vjax:thirdOctet>
               <vjax:fourthOctet class="java.lang.Integer" ref-id="536913846">0</vjax:fourthOctet>
            </vjax:origin>
            <vjax:end class="com.anosym.utilities.geocode.Ipv4" ref-id="184725028">
               <vjax:firstOctet class="java.lang.Integer" ref-id="1559675681">125</vjax:firstOctet>
               <vjax:secondOctet class="java.lang.Integer" ref-id="1283775285">254</vjax:secondOctet>
               <vjax:thirdOctet class="java.lang.Integer" ref-id="643013586">55</vjax:thirdOctet>
               <vjax:fourthOctet class="java.lang.Integer" ref-id="991628198">255</vjax:fourthOctet>
            </vjax:end>
         </vjax:key>
         <vjax:value class="com.anosym.utilities.geocode.CountryIpMapping" value="true" ref-id="1822023066">
            <vjax:ipv4Range class="com.anosym.utilities.geocode.Ipv4Range" references="1182880651"/>
            <vjax:countryCode class="com.anosym.utilities.geocode.CountryCode" ref-id="1506658951">
               <vjax:isoCode class="java.lang.String" ref-id="1437307680">HK</vjax:isoCode>
               <vjax:isoCode2 class="java.lang.String" ref-id="1934116304">HKG</vjax:isoCode2>
               <vjax:internationalDialingCode class="java.lang.String" ref-id="232756689">852</vjax:internationalDialingCode>
               <vjax:name class="java.lang.String" ref-id="1373950836">Hong Kong</vjax:name>
            </vjax:countryCode>
         </vjax:value>
      </vjax:map-entry>
      <vjax:map-entry>
         <vjax:key class="com.anosym.utilities.geocode.Ipv4Range" key="true" ref-id="895770518">
            <vjax:origin class="com.anosym.utilities.geocode.Ipv4" ref-id="1772347689">
               <vjax:firstOctet class="java.lang.Integer" ref-id="101941486">125</vjax:firstOctet>
               <vjax:secondOctet class="java.lang.Integer" ref-id="1786088543">254</vjax:secondOctet>
               <vjax:thirdOctet class="java.lang.Integer" ref-id="1263724435">128</vjax:thirdOctet>
               <vjax:fourthOctet class="java.lang.Integer" ref-id="803310215">0</vjax:fourthOctet>
            </vjax:origin>
            <vjax:end class="com.anosym.utilities.geocode.Ipv4" ref-id="5094816">
               <vjax:firstOctet class="java.lang.Integer" ref-id="1876710279">125</vjax:firstOctet>
               <vjax:secondOctet class="java.lang.Integer" ref-id="1777335664">254</vjax:secondOctet>
               <vjax:thirdOctet class="java.lang.Integer" ref-id="182975078">255</vjax:thirdOctet>
               <vjax:fourthOctet class="java.lang.Integer" ref-id="65553442">255</vjax:fourthOctet>
            </vjax:end>
         </vjax:key>
         <vjax:value class="com.anosym.utilities.geocode.CountryIpMapping" value="true" ref-id="97588783">
            <vjax:ipv4Range class="com.anosym.utilities.geocode.Ipv4Range" references="895770518"/>
            <vjax:countryCode class="com.anosym.utilities.geocode.CountryCode" ref-id="1641590266">
               <vjax:isoCode class="java.lang.String" ref-id="1485187653">CN</vjax:isoCode>
               <vjax:isoCode2 class="java.lang.String" ref-id="1346454890">CHN</vjax:isoCode2>
               <vjax:internationalDialingCode class="java.lang.String" ref-id="2103520410">86</vjax:internationalDialingCode>
               <vjax:name class="java.lang.String" ref-id="1991733956">China</vjax:name>
            </vjax:countryCode>
         </vjax:value>
      </vjax:map-entry>
      <vjax:map-entry>
         <vjax:key class="com.anosym.utilities.geocode.Ipv4Range" key="true" ref-id="221756828">
            <vjax:origin class="com.anosym.utilities.geocode.Ipv4" ref-id="1644653220">
               <vjax:firstOctet class="java.lang.Integer" ref-id="1424648003">125</vjax:firstOctet>
               <vjax:secondOctet class="java.lang.Integer" ref-id="1763806018">254</vjax:secondOctet>
               <vjax:thirdOctet class="java.lang.Integer" ref-id="423481338">0</vjax:thirdOctet>
               <vjax:fourthOctet class="java.lang.Integer" ref-id="690041608">0</vjax:fourthOctet>
            </vjax:origin>
            <vjax:end class="com.anosym.utilities.geocode.Ipv4" ref-id="1117611856">
               <vjax:firstOctet class="java.lang.Integer" ref-id="1810487130">125</vjax:firstOctet>
               <vjax:secondOctet class="java.lang.Integer" ref-id="1161399567">254</vjax:secondOctet>
               <vjax:thirdOctet class="java.lang.Integer" ref-id="1163654986">51</vjax:thirdOctet>
               <vjax:fourthOctet class="java.lang.Integer" ref-id="415776473">255</vjax:fourthOctet>
            </vjax:end>
         </vjax:key>
         <vjax:value class="com.anosym.utilities.geocode.CountryIpMapping" value="true" ref-id="43394373">
            <vjax:ipv4Range class="com.anosym.utilities.geocode.Ipv4Range" references="221756828"/>
            <vjax:countryCode class="com.anosym.utilities.geocode.CountryCode" references="2106830344"/>
         </vjax:value>
      </vjax:map-entry>
      <vjax:map-entry>
         <vjax:key class="com.anosym.utilities.geocode.Ipv4Range" key="true" ref-id="1418981078">
            <vjax:origin class="com.anosym.utilities.geocode.Ipv4" ref-id="1332270678">
               <vjax:firstOctet class="java.lang.Integer" ref-id="1808781524">125</vjax:firstOctet>
               <vjax:secondOctet class="java.lang.Integer" ref-id="412566936">254</vjax:secondOctet>
               <vjax:thirdOctet class="java.lang.Integer" ref-id="1935280836">56</vjax:thirdOctet>
               <vjax:fourthOctet class="java.lang.Integer" ref-id="477693190">0</vjax:fourthOctet>
            </vjax:origin>
            <vjax:end class="com.anosym.utilities.geocode.Ipv4" ref-id="1295571844">
               <vjax:firstOctet class="java.lang.Integer" ref-id="1339285175">125</vjax:firstOctet>
               <vjax:secondOctet class="java.lang.Integer" ref-id="1589832018">254</vjax:secondOctet>
               <vjax:thirdOctet class="java.lang.Integer" ref-id="1315190552">59</vjax:thirdOctet>
               <vjax:fourthOctet class="java.lang.Integer" ref-id="358428893">255</vjax:fourthOctet>
            </vjax:end>
         </vjax:key>
         <vjax:value class="com.anosym.utilities.geocode.CountryIpMapping" value="true" ref-id="422774816">
            <vjax:ipv4Range class="com.anosym.utilities.geocode.Ipv4Range" references="1418981078"/>
            <vjax:countryCode class="com.anosym.utilities.geocode.CountryCode" ref-id="1168029941">
               <vjax:isoCode class="java.lang.String" ref-id="931201160">JP</vjax:isoCode>
               <vjax:isoCode2 class="java.lang.String" ref-id="1984560431">JPN</vjax:isoCode2>
               <vjax:internationalDialingCode class="java.lang.String" ref-id="1938642260">81</vjax:internationalDialingCode>
               <vjax:name class="java.lang.String" ref-id="1138571536">Japan</vjax:name>
            </vjax:countryCode>
         </vjax:value>
      </vjax:map-entry>
   </vjax:ipMappings>
</vjax:CountryIpMappings>