<?xml version="1.0" encoding="UTF-8" standalone="yes" ?>
<vjax:CountryIpMappings xmlns:vjax="http://www.flemax.com/2011/vjax" class="com.anosym.utilities.geocode.CountryIpMappings" ref-id="1756385079">
   <vjax:ipMappings class="java.util.HashMap" ref-id="253811091" map="true">
      <vjax:map-entry>
         <vjax:key class="com.anosym.utilities.geocode.Ipv4Range" key="true" ref-id="152921213">
            <vjax:origin class="com.anosym.utilities.geocode.Ipv4" ref-id="900483495">
               <vjax:firstOctet class="java.lang.Integer" ref-id="1108840056">49</vjax:firstOctet>
               <vjax:secondOctet class="java.lang.Integer" ref-id="411732526">200</vjax:secondOctet>
               <vjax:thirdOctet class="java.lang.Integer" ref-id="796253848">0</vjax:thirdOctet>
               <vjax:fourthOctet class="java.lang.Integer" ref-id="1667818879">0</vjax:fourthOctet>
            </vjax:origin>
            <vjax:end class="com.anosym.utilities.geocode.Ipv4" ref-id="2075338709">
               <vjax:firstOctet class="java.lang.Integer" ref-id="788287589">49</vjax:firstOctet>
               <vjax:secondOctet class="java.lang.Integer" ref-id="922889980">207</vjax:secondOctet>
               <vjax:thirdOctet class="java.lang.Integer" ref-id="1884995226">255</vjax:thirdOctet>
               <vjax:fourthOctet class="java.lang.Integer" ref-id="1436002838">255</vjax:fourthOctet>
            </vjax:end>
         </vjax:key>
         <vjax:value class="com.anosym.utilities.geocode.CountryIpMapping" value="true" ref-id="1478473280">
            <vjax:ipv4Range class="com.anosym.utilities.geocode.Ipv4Range" references="152921213"/>
            <vjax:countryCode class="com.anosym.utilities.geocode.CountryCode" ref-id="1247112170">
               <vjax:isoCode class="java.lang.String" ref-id="773846470">IN</vjax:isoCode>
               <vjax:isoCode2 class="java.lang.String" ref-id="876655058">IND</vjax:isoCode2>
               <vjax:internationalDialingCode class="java.lang.String" ref-id="56257739">91</vjax:internationalDialingCode>
               <vjax:name class="java.lang.String" ref-id="631014693">India</vjax:name>
            </vjax:countryCode>
         </vjax:value>
      </vjax:map-entry>
   </vjax:ipMappings>
</vjax:CountryIpMappings>