<?xml version="1.0" encoding="UTF-8" standalone="yes" ?>
<vjax:CountryIpMappings xmlns:vjax="http://www.flemax.com/2011/vjax" class="com.anosym.utilities.geocode.CountryIpMappings" ref-id="764762284">
   <vjax:ipMappings class="java.util.HashMap" ref-id="670079893" map="true">
      <vjax:map-entry>
         <vjax:key class="com.anosym.utilities.geocode.Ipv4Range" key="true" ref-id="1139305696">
            <vjax:origin class="com.anosym.utilities.geocode.Ipv4" ref-id="628516783">
               <vjax:firstOctet class="java.lang.Integer" ref-id="695142137">164</vjax:firstOctet>
               <vjax:secondOctet class="java.lang.Integer" ref-id="942856879">40</vjax:secondOctet>
               <vjax:thirdOctet class="java.lang.Integer" ref-id="313734140">160</vjax:thirdOctet>
               <vjax:fourthOctet class="java.lang.Integer" ref-id="857337595">0</vjax:fourthOctet>
            </vjax:origin>
            <vjax:end class="com.anosym.utilities.geocode.Ipv4" ref-id="1805171442">
               <vjax:firstOctet class="java.lang.Integer" ref-id="2014944525">164</vjax:firstOctet>
               <vjax:secondOctet class="java.lang.Integer" ref-id="1503002132">40</vjax:secondOctet>
               <vjax:thirdOctet class="java.lang.Integer" ref-id="106692863">167</vjax:thirdOctet>
               <vjax:fourthOctet class="java.lang.Integer" ref-id="38103196">255</vjax:fourthOctet>
            </vjax:end>
         </vjax:key>
         <vjax:value class="com.anosym.utilities.geocode.CountryIpMapping" value="true" ref-id="450288366">
            <vjax:ipv4Range class="com.anosym.utilities.geocode.Ipv4Range" references="1139305696"/>
            <vjax:countryCode class="com.anosym.utilities.geocode.CountryCode" ref-id="1690366154">
               <vjax:isoCode class="java.lang.String" ref-id="922784115">DE</vjax:isoCode>
               <vjax:isoCode2 class="java.lang.String" ref-id="105722171">DEU</vjax:isoCode2>
               <vjax:internationalDialingCode class="java.lang.String" ref-id="903551928">49</vjax:internationalDialingCode>
               <vjax:name class="java.lang.String" ref-id="1140385959">Germany</vjax:name>
            </vjax:countryCode>
         </vjax:value>
      </vjax:map-entry>
      <vjax:map-entry>
         <vjax:key class="com.anosym.utilities.geocode.Ipv4Range" key="true" ref-id="2094494209">
            <vjax:origin class="com.anosym.utilities.geocode.Ipv4" ref-id="264195334">
               <vjax:firstOctet class="java.lang.Integer" ref-id="1482280189">164</vjax:firstOctet>
               <vjax:secondOctet class="java.lang.Integer" ref-id="1872831323">40</vjax:secondOctet>
               <vjax:thirdOctet class="java.lang.Integer" ref-id="1702223844">0</vjax:thirdOctet>
               <vjax:fourthOctet class="java.lang.Integer" ref-id="499000774">0</vjax:fourthOctet>
            </vjax:origin>
            <vjax:end class="com.anosym.utilities.geocode.Ipv4" ref-id="201193400">
               <vjax:firstOctet class="java.lang.Integer" ref-id="1771681102">164</vjax:firstOctet>
               <vjax:secondOctet class="java.lang.Integer" ref-id="1783515659">40</vjax:secondOctet>
               <vjax:thirdOctet class="java.lang.Integer" ref-id="970935987">127</vjax:thirdOctet>
               <vjax:fourthOctet class="java.lang.Integer" ref-id="1940383603">255</vjax:fourthOctet>
            </vjax:end>
         </vjax:key>
         <vjax:value class="com.anosym.utilities.geocode.CountryIpMapping" value="true" ref-id="340552279">
            <vjax:ipv4Range class="com.anosym.utilities.geocode.Ipv4Range" references="2094494209"/>
            <vjax:countryCode class="com.anosym.utilities.geocode.CountryCode" ref-id="1441044483">
               <vjax:isoCode class="java.lang.String" ref-id="314054915">KZ</vjax:isoCode>
               <vjax:isoCode2 class="java.lang.String" ref-id="1953635726">KAZ</vjax:isoCode2>
               <vjax:internationalDialingCode class="java.lang.String" ref-id="1878167899">7</vjax:internationalDialingCode>
               <vjax:name class="java.lang.String" ref-id="420815854">Kazakhstan</vjax:name>
            </vjax:countryCode>
         </vjax:value>
      </vjax:map-entry>
      <vjax:map-entry>
         <vjax:key class="com.anosym.utilities.geocode.Ipv4Range" key="true" ref-id="612229039">
            <vjax:origin class="com.anosym.utilities.geocode.Ipv4" ref-id="618233898">
               <vjax:firstOctet class="java.lang.Integer" ref-id="1131239500">164</vjax:firstOctet>
               <vjax:secondOctet class="java.lang.Integer" ref-id="1069549609">40</vjax:secondOctet>
               <vjax:thirdOctet class="java.lang.Integer" ref-id="1482153073">128</vjax:thirdOctet>
               <vjax:fourthOctet class="java.lang.Integer" ref-id="1883876358">0</vjax:fourthOctet>
            </vjax:origin>
            <vjax:end class="com.anosym.utilities.geocode.Ipv4" ref-id="1958541185">
               <vjax:firstOctet class="java.lang.Integer" ref-id="572355079">164</vjax:firstOctet>
               <vjax:secondOctet class="java.lang.Integer" ref-id="992557840">40</vjax:secondOctet>
               <vjax:thirdOctet class="java.lang.Integer" ref-id="266646984">159</vjax:thirdOctet>
               <vjax:fourthOctet class="java.lang.Integer" ref-id="1884972446">255</vjax:fourthOctet>
            </vjax:end>
         </vjax:key>
         <vjax:value class="com.anosym.utilities.geocode.CountryIpMapping" value="true" ref-id="1053139378">
            <vjax:ipv4Range class="com.anosym.utilities.geocode.Ipv4Range" references="612229039"/>
            <vjax:countryCode class="com.anosym.utilities.geocode.CountryCode" ref-id="1020130360">
               <vjax:isoCode class="java.lang.String" ref-id="1969006519">NL</vjax:isoCode>
               <vjax:isoCode2 class="java.lang.String" ref-id="369564563">NLD</vjax:isoCode2>
               <vjax:internationalDialingCode class="java.lang.String" ref-id="748903217">31</vjax:internationalDialingCode>
               <vjax:name class="java.lang.String" ref-id="414713052">Netherlands</vjax:name>
            </vjax:countryCode>
         </vjax:value>
      </vjax:map-entry>
      <vjax:map-entry>
         <vjax:key class="com.anosym.utilities.geocode.Ipv4Range" key="true" ref-id="470938871">
            <vjax:origin class="com.anosym.utilities.geocode.Ipv4" ref-id="553307472">
               <vjax:firstOctet class="java.lang.Integer" ref-id="834490394">164</vjax:firstOctet>
               <vjax:secondOctet class="java.lang.Integer" ref-id="64353401">40</vjax:secondOctet>
               <vjax:thirdOctet class="java.lang.Integer" ref-id="1403336166">232</vjax:thirdOctet>
               <vjax:fourthOctet class="java.lang.Integer" ref-id="58046961">0</vjax:fourthOctet>
            </vjax:origin>
            <vjax:end class="com.anosym.utilities.geocode.Ipv4" ref-id="637697789">
               <vjax:firstOctet class="java.lang.Integer" ref-id="1843341193">164</vjax:firstOctet>
               <vjax:secondOctet class="java.lang.Integer" ref-id="1436339129">40</vjax:secondOctet>
               <vjax:thirdOctet class="java.lang.Integer" ref-id="688065176">239</vjax:thirdOctet>
               <vjax:fourthOctet class="java.lang.Integer" ref-id="111973937">255</vjax:fourthOctet>
            </vjax:end>
         </vjax:key>
         <vjax:value class="com.anosym.utilities.geocode.CountryIpMapping" value="true" ref-id="750284387">
            <vjax:ipv4Range class="com.anosym.utilities.geocode.Ipv4Range" references="470938871"/>
            <vjax:countryCode class="com.anosym.utilities.geocode.CountryCode" references="1690366154"/>
         </vjax:value>
      </vjax:map-entry>
      <vjax:map-entry>
         <vjax:key class="com.anosym.utilities.geocode.Ipv4Range" key="true" ref-id="485049324">
            <vjax:origin class="com.anosym.utilities.geocode.Ipv4" ref-id="5717125">
               <vjax:firstOctet class="java.lang.Integer" ref-id="1598439407">164</vjax:firstOctet>
               <vjax:secondOctet class="java.lang.Integer" ref-id="2098173126">40</vjax:secondOctet>
               <vjax:thirdOctet class="java.lang.Integer" ref-id="166761295">208</vjax:thirdOctet>
               <vjax:fourthOctet class="java.lang.Integer" ref-id="290925730">0</vjax:fourthOctet>
            </vjax:origin>
            <vjax:end class="com.anosym.utilities.geocode.Ipv4" ref-id="1915963538">
               <vjax:firstOctet class="java.lang.Integer" ref-id="81896401">164</vjax:firstOctet>
               <vjax:secondOctet class="java.lang.Integer" ref-id="2043277527">40</vjax:secondOctet>
               <vjax:thirdOctet class="java.lang.Integer" ref-id="954397112">223</vjax:thirdOctet>
               <vjax:fourthOctet class="java.lang.Integer" ref-id="996901941">255</vjax:fourthOctet>
            </vjax:end>
         </vjax:key>
         <vjax:value class="com.anosym.utilities.geocode.CountryIpMapping" value="true" ref-id="263508493">
            <vjax:ipv4Range class="com.anosym.utilities.geocode.Ipv4Range" references="485049324"/>
            <vjax:countryCode class="com.anosym.utilities.geocode.CountryCode" ref-id="993131823">
               <vjax:isoCode class="java.lang.String" ref-id="1323644677">GB</vjax:isoCode>
               <vjax:isoCode2 class="java.lang.String" ref-id="712987066">GBR</vjax:isoCode2>
               <vjax:internationalDialingCode class="java.lang.String" ref-id="214868002">44</vjax:internationalDialingCode>
               <vjax:name class="java.lang.String" ref-id="1366499007">United Kingdom</vjax:name>
            </vjax:countryCode>
         </vjax:value>
      </vjax:map-entry>
      <vjax:map-entry>
         <vjax:key class="com.anosym.utilities.geocode.Ipv4Range" key="true" ref-id="1083870599">
            <vjax:origin class="com.anosym.utilities.geocode.Ipv4" ref-id="675961737">
               <vjax:firstOctet class="java.lang.Integer" ref-id="700421129">164</vjax:firstOctet>
               <vjax:secondOctet class="java.lang.Integer" ref-id="1620045896">40</vjax:secondOctet>
               <vjax:thirdOctet class="java.lang.Integer" ref-id="166213759">184</vjax:thirdOctet>
               <vjax:fourthOctet class="java.lang.Integer" ref-id="1825906413">0</vjax:fourthOctet>
            </vjax:origin>
            <vjax:end class="com.anosym.utilities.geocode.Ipv4" ref-id="467767661">
               <vjax:firstOctet class="java.lang.Integer" ref-id="1980930407">164</vjax:firstOctet>
               <vjax:secondOctet class="java.lang.Integer" ref-id="1058371008">40</vjax:secondOctet>
               <vjax:thirdOctet class="java.lang.Integer" ref-id="434483355">191</vjax:thirdOctet>
               <vjax:fourthOctet class="java.lang.Integer" ref-id="917347685">255</vjax:fourthOctet>
            </vjax:end>
         </vjax:key>
         <vjax:value class="com.anosym.utilities.geocode.CountryIpMapping" value="true" ref-id="1077439982">
            <vjax:ipv4Range class="com.anosym.utilities.geocode.Ipv4Range" references="1083870599"/>
            <vjax:countryCode class="com.anosym.utilities.geocode.CountryCode" ref-id="689324956">
               <vjax:isoCode class="java.lang.String" ref-id="1957743574">PL</vjax:isoCode>
               <vjax:isoCode2 class="java.lang.String" ref-id="51808884">POL</vjax:isoCode2>
               <vjax:internationalDialingCode class="java.lang.String" ref-id="1021036353">48</vjax:internationalDialingCode>
               <vjax:name class="java.lang.String" ref-id="16161694">Poland</vjax:name>
            </vjax:countryCode>
         </vjax:value>
      </vjax:map-entry>
      <vjax:map-entry>
         <vjax:key class="com.anosym.utilities.geocode.Ipv4Range" key="true" ref-id="376064456">
            <vjax:origin class="com.anosym.utilities.geocode.Ipv4" ref-id="1599705238">
               <vjax:firstOctet class="java.lang.Integer" ref-id="1898158273">164</vjax:firstOctet>
               <vjax:secondOctet class="java.lang.Integer" ref-id="1476518126">40</vjax:secondOctet>
               <vjax:thirdOctet class="java.lang.Integer" ref-id="1666602597">224</vjax:thirdOctet>
               <vjax:fourthOctet class="java.lang.Integer" ref-id="960639958">0</vjax:fourthOctet>
            </vjax:origin>
            <vjax:end class="com.anosym.utilities.geocode.Ipv4" ref-id="693715960">
               <vjax:firstOctet class="java.lang.Integer" ref-id="595420157">164</vjax:firstOctet>
               <vjax:secondOctet class="java.lang.Integer" ref-id="2100267326">40</vjax:secondOctet>
               <vjax:thirdOctet class="java.lang.Integer" ref-id="1004242343">231</vjax:thirdOctet>
               <vjax:fourthOctet class="java.lang.Integer" ref-id="1227077028">255</vjax:fourthOctet>
            </vjax:end>
         </vjax:key>
         <vjax:value class="com.anosym.utilities.geocode.CountryIpMapping" value="true" ref-id="1198147455">
            <vjax:ipv4Range class="com.anosym.utilities.geocode.Ipv4Range" references="376064456"/>
            <vjax:countryCode class="com.anosym.utilities.geocode.CountryCode" ref-id="332934521">
               <vjax:isoCode class="java.lang.String" ref-id="1435594012">BA</vjax:isoCode>
               <vjax:isoCode2 class="java.lang.String" ref-id="1049785639">BIH</vjax:isoCode2>
               <vjax:internationalDialingCode class="java.lang.String" ref-id="21590921">387</vjax:internationalDialingCode>
               <vjax:name class="java.lang.String" ref-id="2101356551">Bosnia and Herzegovina</vjax:name>
            </vjax:countryCode>
         </vjax:value>
      </vjax:map-entry>
      <vjax:map-entry>
         <vjax:key class="com.anosym.utilities.geocode.Ipv4Range" key="true" ref-id="1656863539">
            <vjax:origin class="com.anosym.utilities.geocode.Ipv4" ref-id="310118266">
               <vjax:firstOctet class="java.lang.Integer" ref-id="214885393">164</vjax:firstOctet>
               <vjax:secondOctet class="java.lang.Integer" ref-id="1658789544">40</vjax:secondOctet>
               <vjax:thirdOctet class="java.lang.Integer" ref-id="643160654">192</vjax:thirdOctet>
               <vjax:fourthOctet class="java.lang.Integer" ref-id="1315916427">0</vjax:fourthOctet>
            </vjax:origin>
            <vjax:end class="com.anosym.utilities.geocode.Ipv4" ref-id="1820791783">
               <vjax:firstOctet class="java.lang.Integer" ref-id="405527131">164</vjax:firstOctet>
               <vjax:secondOctet class="java.lang.Integer" ref-id="1728878786">40</vjax:secondOctet>
               <vjax:thirdOctet class="java.lang.Integer" ref-id="1812012392">207</vjax:thirdOctet>
               <vjax:fourthOctet class="java.lang.Integer" ref-id="1026674237">255</vjax:fourthOctet>
            </vjax:end>
         </vjax:key>
         <vjax:value class="com.anosym.utilities.geocode.CountryIpMapping" value="true" ref-id="282797614">
            <vjax:ipv4Range class="com.anosym.utilities.geocode.Ipv4Range" references="1656863539"/>
            <vjax:countryCode class="com.anosym.utilities.geocode.CountryCode" references="1690366154"/>
         </vjax:value>
      </vjax:map-entry>
      <vjax:map-entry>
         <vjax:key class="com.anosym.utilities.geocode.Ipv4Range" key="true" ref-id="1346636020">
            <vjax:origin class="com.anosym.utilities.geocode.Ipv4" ref-id="598187687">
               <vjax:firstOctet class="java.lang.Integer" ref-id="1369503802">164</vjax:firstOctet>
               <vjax:secondOctet class="java.lang.Integer" ref-id="520671668">40</vjax:secondOctet>
               <vjax:thirdOctet class="java.lang.Integer" ref-id="2080346198">168</vjax:thirdOctet>
               <vjax:fourthOctet class="java.lang.Integer" ref-id="1197292979">0</vjax:fourthOctet>
            </vjax:origin>
            <vjax:end class="com.anosym.utilities.geocode.Ipv4" ref-id="981325663">
               <vjax:firstOctet class="java.lang.Integer" ref-id="466009081">164</vjax:firstOctet>
               <vjax:secondOctet class="java.lang.Integer" ref-id="341763758">40</vjax:secondOctet>
               <vjax:thirdOctet class="java.lang.Integer" ref-id="1652208628">175</vjax:thirdOctet>
               <vjax:fourthOctet class="java.lang.Integer" ref-id="1706855086">255</vjax:fourthOctet>
            </vjax:end>
         </vjax:key>
         <vjax:value class="com.anosym.utilities.geocode.CountryIpMapping" value="true" ref-id="1026873776">
            <vjax:ipv4Range class="com.anosym.utilities.geocode.Ipv4Range" references="1346636020"/>
            <vjax:countryCode class="com.anosym.utilities.geocode.CountryCode" ref-id="1797780538">
               <vjax:isoCode class="java.lang.String" ref-id="202588876">SK</vjax:isoCode>
               <vjax:isoCode2 class="java.lang.String" ref-id="1149658437">SVK</vjax:isoCode2>
               <vjax:internationalDialingCode class="java.lang.String" ref-id="1398978600">421</vjax:internationalDialingCode>
               <vjax:name class="java.lang.String" ref-id="1982362844">Slovakia</vjax:name>
            </vjax:countryCode>
         </vjax:value>
      </vjax:map-entry>
      <vjax:map-entry>
         <vjax:key class="com.anosym.utilities.geocode.Ipv4Range" key="true" ref-id="581432407">
            <vjax:origin class="com.anosym.utilities.geocode.Ipv4" ref-id="790511018">
               <vjax:firstOctet class="java.lang.Integer" ref-id="1784839184">164</vjax:firstOctet>
               <vjax:secondOctet class="java.lang.Integer" ref-id="1740584192">40</vjax:secondOctet>
               <vjax:thirdOctet class="java.lang.Integer" ref-id="976275510">176</vjax:thirdOctet>
               <vjax:fourthOctet class="java.lang.Integer" ref-id="1487433490">0</vjax:fourthOctet>
            </vjax:origin>
            <vjax:end class="com.anosym.utilities.geocode.Ipv4" ref-id="437531703">
               <vjax:firstOctet class="java.lang.Integer" ref-id="611324993">164</vjax:firstOctet>
               <vjax:secondOctet class="java.lang.Integer" ref-id="977390103">40</vjax:secondOctet>
               <vjax:thirdOctet class="java.lang.Integer" ref-id="893045218">183</vjax:thirdOctet>
               <vjax:fourthOctet class="java.lang.Integer" ref-id="647770043">255</vjax:fourthOctet>
            </vjax:end>
         </vjax:key>
         <vjax:value class="com.anosym.utilities.geocode.CountryIpMapping" value="true" ref-id="1476506058">
            <vjax:ipv4Range class="com.anosym.utilities.geocode.Ipv4Range" references="581432407"/>
            <vjax:countryCode class="com.anosym.utilities.geocode.CountryCode" ref-id="860199542">
               <vjax:isoCode class="java.lang.String" ref-id="513790790">SE</vjax:isoCode>
               <vjax:isoCode2 class="java.lang.String" ref-id="250062943">SWE</vjax:isoCode2>
               <vjax:internationalDialingCode class="java.lang.String" ref-id="182385822">46</vjax:internationalDialingCode>
               <vjax:name class="java.lang.String" ref-id="899346085">Sweden</vjax:name>
            </vjax:countryCode>
         </vjax:value>
      </vjax:map-entry>
      <vjax:map-entry>
         <vjax:key class="com.anosym.utilities.geocode.Ipv4Range" key="true" ref-id="949144600">
            <vjax:origin class="com.anosym.utilities.geocode.Ipv4" ref-id="1463775721">
               <vjax:firstOctet class="java.lang.Integer" ref-id="105882815">164</vjax:firstOctet>
               <vjax:secondOctet class="java.lang.Integer" ref-id="1456011989">40</vjax:secondOctet>
               <vjax:thirdOctet class="java.lang.Integer" ref-id="617341558">248</vjax:thirdOctet>
               <vjax:fourthOctet class="java.lang.Integer" ref-id="1166066649">0</vjax:fourthOctet>
            </vjax:origin>
            <vjax:end class="com.anosym.utilities.geocode.Ipv4" ref-id="146407221">
               <vjax:firstOctet class="java.lang.Integer" ref-id="1797387532">164</vjax:firstOctet>
               <vjax:secondOctet class="java.lang.Integer" ref-id="39787975">40</vjax:secondOctet>
               <vjax:thirdOctet class="java.lang.Integer" ref-id="849081608">255</vjax:thirdOctet>
               <vjax:fourthOctet class="java.lang.Integer" ref-id="485751341">255</vjax:fourthOctet>
            </vjax:end>
         </vjax:key>
         <vjax:value class="com.anosym.utilities.geocode.CountryIpMapping" value="true" ref-id="1437445940">
            <vjax:ipv4Range class="com.anosym.utilities.geocode.Ipv4Range" references="949144600"/>
            <vjax:countryCode class="com.anosym.utilities.geocode.CountryCode" ref-id="1790198231">
               <vjax:isoCode class="java.lang.String" ref-id="1615773947">MK</vjax:isoCode>
               <vjax:isoCode2 class="java.lang.String" ref-id="1382010914">MKD</vjax:isoCode2>
               <vjax:internationalDialingCode class="java.lang.String" ref-id="274305646">389</vjax:internationalDialingCode>
               <vjax:name class="java.lang.String" ref-id="1755085860">Macedonia</vjax:name>
            </vjax:countryCode>
         </vjax:value>
      </vjax:map-entry>
      <vjax:map-entry>
         <vjax:key class="com.anosym.utilities.geocode.Ipv4Range" key="true" ref-id="1592365702">
            <vjax:origin class="com.anosym.utilities.geocode.Ipv4" ref-id="1356441726">
               <vjax:firstOctet class="java.lang.Integer" ref-id="29692330">164</vjax:firstOctet>
               <vjax:secondOctet class="java.lang.Integer" ref-id="822784206">40</vjax:secondOctet>
               <vjax:thirdOctet class="java.lang.Integer" ref-id="886947209">240</vjax:thirdOctet>
               <vjax:fourthOctet class="java.lang.Integer" ref-id="1237747836">0</vjax:fourthOctet>
            </vjax:origin>
            <vjax:end class="com.anosym.utilities.geocode.Ipv4" ref-id="153791163">
               <vjax:firstOctet class="java.lang.Integer" ref-id="1345249200">164</vjax:firstOctet>
               <vjax:secondOctet class="java.lang.Integer" ref-id="895468784">40</vjax:secondOctet>
               <vjax:thirdOctet class="java.lang.Integer" ref-id="578454512">247</vjax:thirdOctet>
               <vjax:fourthOctet class="java.lang.Integer" ref-id="426513215">255</vjax:fourthOctet>
            </vjax:end>
         </vjax:key>
         <vjax:value class="com.anosym.utilities.geocode.CountryIpMapping" value="true" ref-id="107190819">
            <vjax:ipv4Range class="com.anosym.utilities.geocode.Ipv4Range" references="1592365702"/>
            <vjax:countryCode class="com.anosym.utilities.geocode.CountryCode" references="689324956"/>
         </vjax:value>
      </vjax:map-entry>
   </vjax:ipMappings>
</vjax:CountryIpMappings>